<?xml version='1.0' encoding='UTF-8'?>
<root>
 <tabbed_widget name="Main Window" parent="main_window">
  <Tab tab_name="Pose Observer" containers="1">
   <Container>
    <DockSplitter sizes="0.332903;0.334194;0.332903" orientation="-" count="3">
     <DockArea name="...">
      <plot style="Lines" mode="TimeSeries" flip_x="false" flip_y="false">
       <range bottom="0.155737" top="2.029514" right="10.162088" left="0.000181"/>
       <limitY/>
       <curve color="#ff0000" name="/tmr4243/state/eta/data[0]">
        <transform alias="surge" name="Scale/Offset">
         <options value_offset="0.0" time_offset="0.0" value_scale="1.0"/>
        </transform>
       </curve>
       <curve color="#00ff00" name="/tmr4243/observer/eta[0]">
        <transform alias="surge observed" name="Scale/Offset">
         <options value_offset="0.0" time_offset="0.0" value_scale="1.0"/>
        </transform>
       </curve>
       <curve color="#0000ff" name="/tmr4243/control/reference/eta_d[0]">
        <transform alias="surge reference" name="Scale/Offset">
         <options value_offset="0.0" time_offset="0.0" value_scale="1.0"/>
        </transform>
       </curve>
      </plot>
     </DockArea>
     <DockArea name="...">
      <plot style="Lines" mode="TimeSeries" flip_x="false" flip_y="false">
       <range bottom="-0.003437" top="0.140930" right="10.162088" left="0.000181"/>
       <limitY/>
       <curve color="#ff0000" name="/tmr4243/state/eta/data[1]">
        <transform alias="sway" name="Scale/Offset">
         <options value_offset="0.0" time_offset="0.0" value_scale="1.0"/>
        </transform>
       </curve>
       <curve color="#00ff00" name="/tmr4243/observer/eta[1]">
        <transform alias="sway observed" name="Scale/Offset">
         <options value_offset="0.0" time_offset="0.0" value_scale="1.0"/>
        </transform>
       </curve>
       <curve color="#0000ff" name="/tmr4243/control/reference/eta_d[1]">
        <transform alias="sway reference" name="Scale/Offset">
         <options value_offset="0.0" time_offset="0.0" value_scale="1.0"/>
        </transform>
       </curve>
      </plot>
     </DockArea>
     <DockArea name="...">
      <plot style="Lines" mode="TimeSeries" flip_x="false" flip_y="false">
       <range bottom="-0.002340" top="0.095923" right="10.162088" left="0.000181"/>
       <limitY/>
       <curve color="#ff0000" name="/tmr4243/state/eta/data[2]">
        <transform alias="heading" name="Scale/Offset">
         <options value_offset="0.0" time_offset="0.0" value_scale="1.0"/>
        </transform>
       </curve>
       <curve color="#00ff00" name="/tmr4243/observer/eta[2]">
        <transform alias="heading observed" name="Scale/Offset">
         <options value_offset="0.0" time_offset="0.0" value_scale="1.0"/>
        </transform>
       </curve>
       <curve color="#0000ff" name="/tmr4243/control/reference/eta_d[2]">
        <transform alias="heading desired" name="Scale/Offset">
         <options value_offset="0.0" time_offset="0.0" value_scale="1.0"/>
        </transform>
       </curve>
      </plot>
     </DockArea>
    </DockSplitter>
   </Container>
  </Tab>
  <Tab tab_name="Observer" containers="1">
   <Container>
    <DockSplitter sizes="0.5;0.5" orientation="-" count="2">
     <DockSplitter sizes="0.336735;0.336735;0.326531" orientation="|" count="3">
      <DockArea name="...">
       <plot style="Lines" mode="TimeSeries" flip_x="false" flip_y="false">
        <range bottom="-0.202167" top="-0.026649" right="10.108247" left="0.001626"/>
        <limitY/>
        <curve color="#ff0000" name="/tmr4243/observer/bias[0]"/>
       </plot>
      </DockArea>
      <DockArea name="...">
       <plot style="Lines" mode="TimeSeries" flip_x="false" flip_y="false">
        <range bottom="-0.000175" top="0.000356" right="10.108247" left="0.001626"/>
        <limitY/>
        <curve color="#ff0000" name="/tmr4243/observer/bias[1]"/>
       </plot>
      </DockArea>
      <DockArea name="...">
       <plot style="Lines" mode="TimeSeries" flip_x="false" flip_y="false">
        <range bottom="-0.009391" top="0.004138" right="10.108247" left="0.001626"/>
        <limitY/>
        <curve color="#ff0000" name="/tmr4243/observer/bias[2]"/>
       </plot>
      </DockArea>
     </DockSplitter>
     <DockSplitter sizes="0.336735;0.336735;0.326531" orientation="|" count="3">
      <DockArea name="...">
       <plot style="Lines" mode="TimeSeries" flip_x="false" flip_y="false">
        <range bottom="0.205373" top="0.952893" right="10.108247" left="0.001626"/>
        <limitY/>
        <curve color="#ff0000" name="/tmr4243/observer/nu[0]"/>
       </plot>
      </DockArea>
      <DockArea name="...">
       <plot style="Lines" mode="TimeSeries" flip_x="false" flip_y="false">
        <range bottom="-0.000604" top="-0.000272" right="10.108247" left="0.001626"/>
        <limitY/>
        <curve color="#ff0000" name="/tmr4243/observer/nu[1]"/>
       </plot>
      </DockArea>
      <DockArea name="...">
       <plot style="Lines" mode="TimeSeries" flip_x="false" flip_y="false">
        <range bottom="-0.000562" top="0.008496" right="10.108247" left="0.001626"/>
        <limitY/>
        <curve color="#ff0000" name="/tmr4243/observer/nu[2]"/>
       </plot>
      </DockArea>
     </DockSplitter>
    </DockSplitter>
   </Container>
  </Tab>
  <Tab tab_name="map" containers="1">
   <Container>
    <DockSplitter sizes="1" orientation="-" count="1">
     <DockArea name="...">
      <plot style="Lines" mode="XYPlot" flip_x="false" flip_y="false">
       <range bottom="-0.732185" top="0.870386" right="1.979489" left="0.156957"/>
       <limitY/>
       <curve curve_y="/tmr4243/state/eta/data[1]" color="#ff0000" curve_x="/tmr4243/state/eta/data[0]" name="/tmr4243/state/eta/data[[0];1]]"/>
       <curve curve_y="/tmr4243/observer/eta[1]" color="#00ff00" curve_x="/tmr4243/observer/eta[0]" name="/tmr4243/observer/eta[[0];1]]"/>
      </plot>
     </DockArea>
    </DockSplitter>
   </Container>
  </Tab>
  <Tab tab_name="Thrust Allocator" containers="1">
   <Container>
    <DockSplitter sizes="0.5;0.5" orientation="-" count="2">
     <DockSplitter sizes="0.336735;0.336735;0.326531" orientation="|" count="3">
      <DockArea name="...">
       <plot style="Lines" mode="TimeSeries" flip_x="false" flip_y="false">
        <range bottom="0.935387" top="2.904905" right="10.154839" left="0.000000"/>
        <limitY/>
        <curve color="#ff0000" name="/tmr4243/command/tau/data[0]">
         <transform alias="tau surge requested" name="Scale/Offset">
          <options value_offset="0.0" time_offset="0.0" value_scale="1.0"/>
         </transform>
        </curve>
        <curve color="#00ff00" name="/tmr4243/state/tau/data[0]">
         <transform alias="tau surge" name="Scale/Offset">
          <options value_offset="0.0" time_offset="0.0" value_scale="1.0"/>
         </transform>
        </curve>
       </plot>
      </DockArea>
      <DockArea name="...">
       <plot style="Lines" mode="TimeSeries" flip_x="false" flip_y="false">
        <range bottom="-0.100000" top="0.100000" right="10.154839" left="0.000000"/>
        <limitY/>
        <curve color="#ff0000" name="/tmr4243/command/tau/data[1]">
         <transform alias="tau sway requested" name="Scale/Offset">
          <options value_offset="0.0" time_offset="0.0" value_scale="1.0"/>
         </transform>
        </curve>
        <curve color="#00ff00" name="/tmr4243/state/tau/data[1]">
         <transform alias="tau sway" name="Scale/Offset">
          <options value_offset="0.0" time_offset="0.0" value_scale="1.0"/>
         </transform>
        </curve>
       </plot>
      </DockArea>
      <DockArea name="...">
       <plot style="Lines" mode="TimeSeries" flip_x="false" flip_y="false">
        <range bottom="-0.100000" top="0.100000" right="10.154839" left="0.000000"/>
        <limitY/>
        <curve color="#ff0000" name="/tmr4243/command/tau/data[2]">
         <transform alias="tau yaw requested" name="Scale/Offset">
          <options value_offset="0.0" time_offset="0.0" value_scale="1.0"/>
         </transform>
        </curve>
        <curve color="#00ff00" name="/tmr4243/state/tau/data[2]">
         <transform alias="tau yaw" name="Scale/Offset">
          <options value_offset="0.0" time_offset="0.0" value_scale="1.0"/>
         </transform>
        </curve>
       </plot>
      </DockArea>
     </DockSplitter>
     <DockSplitter sizes="0.197917;0.197917;0.208333;0.197917;0.197917" orientation="|" count="5">
      <DockArea name="...">
       <plot style="Lines" mode="TimeSeries" flip_x="false" flip_y="false">
        <range bottom="-0.100000" top="0.100000" right="10.154839" left="0.000000"/>
        <limitY/>
        <curve color="#ff0000" name="/tmr4243/command/u/data[0]">
         <transform alias="Tunnel" name="Scale/Offset">
          <options value_offset="0.0" time_offset="0.0" value_scale="1.0"/>
         </transform>
        </curve>
       </plot>
      </DockArea>
      <DockArea name="...">
       <plot style="Lines" mode="TimeSeries" flip_x="false" flip_y="false">
        <range bottom="0.467694" top="1.452452" right="10.154839" left="0.000000"/>
        <limitY/>
        <curve color="#ff0000" name="/tmr4243/command/u/data[1]">
         <transform alias="Azimuth 0 surge" name="Scale/Offset">
          <options value_offset="0.0" time_offset="0.0" value_scale="1.0"/>
         </transform>
        </curve>
       </plot>
      </DockArea>
      <DockArea name="...">
       <plot style="Lines" mode="TimeSeries" flip_x="false" flip_y="false">
        <range bottom="0.467694" top="1.452452" right="10.154839" left="0.000000"/>
        <limitY/>
        <curve color="#ff0000" name="/tmr4243/command/u/data[2]">
         <transform alias="Azimuth 0 sway" name="Scale/Offset">
          <options value_offset="0.0" time_offset="0.0" value_scale="1.0"/>
         </transform>
        </curve>
       </plot>
      </DockArea>
      <DockArea name="...">
       <plot style="Lines" mode="TimeSeries" flip_x="false" flip_y="false">
        <range bottom="-0.100000" top="0.100000" right="10.154839" left="0.000000"/>
        <limitY/>
        <curve color="#ff0000" name="/tmr4243/command/u/data[3]">
         <transform alias="Azimuth 1 surge" name="Scale/Offset">
          <options value_offset="0.0" time_offset="0.0" value_scale="1.0"/>
         </transform>
        </curve>
       </plot>
      </DockArea>
      <DockArea name="...">
       <plot style="Lines" mode="TimeSeries" flip_x="false" flip_y="false">
        <range bottom="-0.100000" top="0.100000" right="10.154839" left="0.000000"/>
        <limitY/>
        <curve color="#ff0000" name="/tmr4243/command/u/data[4]">
         <transform alias="Azimuth 1 sway" name="Scale/Offset">
          <options value_offset="0.0" time_offset="0.0" value_scale="1.0"/>
         </transform>
        </curve>
       </plot>
      </DockArea>
     </DockSplitter>
    </DockSplitter>
   </Container>
  </Tab>
  <Tab tab_name="Joystick" containers="1">
   <Container>
    <DockSplitter sizes="0.5;0.5" orientation="-" count="2">
     <DockSplitter sizes="0.5;0.5" orientation="|" count="2">
      <DockArea name="...">
       <plot style="Lines" mode="TimeSeries" flip_x="false" flip_y="false">
        <range bottom="0.000000" top="1.000000" right="1.000000" left="0.000000"/>
        <limitY/>
       </plot>
      </DockArea>
      <DockArea name="...">
       <plot style="Lines" mode="TimeSeries" flip_x="false" flip_y="false">
        <range bottom="0.000000" top="1.000000" right="1.000000" left="0.000000"/>
        <limitY/>
       </plot>
      </DockArea>
     </DockSplitter>
     <DockSplitter sizes="0.5;0.5" orientation="|" count="2">
      <DockArea name="...">
       <plot style="Lines" mode="XYPlot" flip_x="true" flip_y="false">
        <range bottom="0.000000" top="1.000000" right="0.000000" left="1.000000"/>
        <limitY/>
       </plot>
      </DockArea>
      <DockArea name="...">
       <plot style="Lines" mode="XYPlot" flip_x="true" flip_y="false">
        <range bottom="0.000000" top="1.000000" right="0.000000" left="1.000000"/>
        <limitY/>
       </plot>
      </DockArea>
     </DockSplitter>
    </DockSplitter>
   </Container>
  </Tab>
  <currentTabIndex index="0"/>
 </tabbed_widget>
 <use_relative_time_offset enabled="1"/>
 <!-- - - - - - - - - - - - - - - -->
 <!-- - - - - - - - - - - - - - - -->
 <Plugins>
  <plugin ID="DataLoad CSV">
   <parameters delimiter="0" time_axis=""/>
  </plugin>
  <plugin ID="DataLoad MCAP"/>
  <plugin ID="DataLoad ROS2 bags">
   <use_header_stamp value="false"/>
   <discard_large_arrays value="true"/>
   <max_array_size value="100"/>
   <boolean_strings_to_number value="true"/>
   <remove_suffix_from_strings value="true"/>
   <selected_topics value=""/>
  </plugin>
  <plugin ID="DataLoad ULog"/>
  <plugin ID="ROS2 Topic Subscriber">
   <use_header_stamp value="false"/>
   <discard_large_arrays value="true"/>
   <max_array_size value="100"/>
   <boolean_strings_to_number value="true"/>
   <remove_suffix_from_strings value="true"/>
   <selected_topics value="/tmr4243/command/u;/tmr4243/state/eta;/tmr4243/state/tau;/joy;/tmr4243/command/tau;/tmr4243/control/reference;/tmr4243/observer"/>
  </plugin>
  <plugin ID="UDP Server"/>
  <plugin ID="WebSocket Server"/>
  <plugin ID="ZMQ Subscriber"/>
  <plugin ID="Fast Fourier Transform"/>
  <plugin ID="Quaternion to RPY"/>
  <plugin ID="Reactive Script Editor">
   <library code="--[[ Helper function to create a series from arrays&#xa;&#xa; new_series: a series previously created with ScatterXY.new(name)&#xa; prefix:     prefix of the timeseries, before the index of the array&#xa; suffix_X:   suffix to complete the name of the series containing the X value. If [nil], use the index of the array.&#xa; suffix_Y:   suffix to complete the name of the series containing the Y value&#xa; timestamp:   usually the tracker_time variable&#xa;              &#xa; Example:&#xa; &#xa; Assuming we have multiple series in the form:&#xa; &#xa;   /trajectory/node.{X}/position/x&#xa;   /trajectory/node.{X}/position/y&#xa;   &#xa; where {N} is the index of the array (integer). We can create a reactive series from the array with:&#xa; &#xa;   new_series = ScatterXY.new(&quot;my_trajectory&quot;) &#xa;   CreateSeriesFromArray( new_series, &quot;/trajectory/node&quot;, &quot;position/x&quot;, &quot;position/y&quot;, tracker_time );&#xa;--]]&#xa;&#xa;function CreateSeriesFromArray( new_series, prefix, suffix_X, suffix_Y, timestamp )&#xa;  &#xa;  --- clear previous values&#xa;  new_series:clear()&#xa;  &#xa;  --- Append points to new_series&#xa;  index = 0&#xa;  while(true) do&#xa;&#xa;    x = index;&#xa;    -- if not nil, get the X coordinate from a series&#xa;    if suffix_X ~= nil then &#xa;      series_x = TimeseriesView.find( string.format( &quot;%s.%d/%s&quot;, prefix, index, suffix_X) )&#xa;      if series_x == nil then break end&#xa;      x = series_x:atTime(timestamp)&#x9; &#xa;    end&#xa;    &#xa;    series_y = TimeseriesView.find( string.format( &quot;%s.%d/%s&quot;, prefix, index, suffix_Y) )&#xa;    if series_y == nil then break end &#xa;    y = series_y:atTime(timestamp)&#xa;    &#xa;    new_series:push_back(x,y)&#xa;    index = index+1&#xa;  end&#xa;end&#xa;&#xa;--[[ Similar to the built-in function GetSeriesNames(), but select only the names with a give prefix. --]]&#xa;&#xa;function GetSeriesNamesByPrefix(prefix)&#xa;  -- GetSeriesNames(9 is a built-in function&#xa;  all_names = GetSeriesNames()&#xa;  filtered_names = {}&#xa;  for i, name in ipairs(all_names)  do&#xa;    -- check the prefix&#xa;    if name:find(prefix, 1, #prefix) then&#xa;      table.insert(filtered_names, name);&#xa;    end&#xa;  end&#xa;  return filtered_names&#xa;end&#xa;&#xa;--[[ Modify an existing series, applying offsets to all their X and Y values&#xa;&#xa; series: an existing timeseries, obtained with TimeseriesView.find(name)&#xa; delta_x: offset to apply to each x value&#xa; delta_y: offset to apply to each y value &#xa;  &#xa;--]]&#xa;&#xa;function ApplyOffsetInPlace(series, delta_x, delta_y)&#xa;  -- use C++ indeces, not Lua indeces&#xa;  for index=0, series:size()-1 do&#xa;    x,y = series:at(index)&#xa;    series:set(index, x + delta_x, y + delta_y)&#xa;  end&#xa;end&#xa;"/>
   <scripts/>
  </plugin>
  <plugin ID="CSV Exporter"/>
  <plugin ID="ROS2 Topic Re-Publisher"/>
 </Plugins>
 <!-- - - - - - - - - - - - - - - -->
 <previouslyLoaded_Datafiles/>
 <previouslyLoaded_Streamer name="ROS2 Topic Subscriber"/>
 <!-- - - - - - - - - - - - - - - -->
 <customMathEquations/>
 <snippets/>
 <!-- - - - - - - - - - - - - - - -->
</root>

